jVex/__init__.py
jVex/bus.py
jVex/screen.py
jVex/vex_translator.py
jVex-0.1.1.dist-info/METADATA
jVex-0.1.1.dist-info/WHEEL
jVex-0.1.1.dist-info/top_level.txt
jVex-0.1.1.dist-info/RECORD
