Metadata-Version: 2.1
Name: jVex
Version: 0.1.1
Summary: Jonathan's Vex COM Controller
Author: Jonathan Armstrong
Author-email: jbarmstrong@me.com
Keywords: python,vex
Classifier: Development Status :: 1 - Planning
Classifier: Intended Audience :: Education
Classifier: Programming Language :: Python :: 3
Requires-Dist: pyserial
